BigNumber/BigNumber.py
BigNumber/BigNumber_versus_mpf.py
BigNumber-1.dist-info/LICENSE
BigNumber-1.dist-info/METADATA
BigNumber-1.dist-info/WHEEL
BigNumber-1.dist-info/entry_points.txt
BigNumber-1.dist-info/top_level.txt
BigNumber-1.dist-info/RECORD
