Metadata-Version: 2.1
Name: BigNumber
Version: 1
Summary: This package contains implementation of the library "BigNumber".
Home-page: https://github.com/GlobalCreativeCommunityFounder/BigNumber
Author: GlobalCreativeCommunityFounder
Author-email: globalcreativecommunityfounder@gmail.com
License: MIT
Platform: UNKNOWN
Classifier: Programming Language :: Python :: 3
Classifier: Programming Language :: Python :: 3.7
